backtesting_server/__init__.py
backtesting_server/main.py
backtesting_server-0.7.0.dist-info/LICENSE
backtesting_server-0.7.0.dist-info/METADATA
backtesting_server-0.7.0.dist-info/WHEEL
backtesting_server-0.7.0.dist-info/RECORD
