Metadata-Version: 2.1
Name: backtesting-server
Version: 0.7.0
Summary: Package to interact with MySQL server, recording results of the backtesting.
License: MIT
Author: hnewey7
Author-email: hnewey7@gmail.com
Requires-Python: >=3.11,<4.0
Classifier: License :: OSI Approved :: MIT License
Classifier: Programming Language :: Python :: 3
Classifier: Programming Language :: Python :: 3.11
Classifier: Programming Language :: Python :: 3.12
Requires-Dist: ig-package (>=1.2.0,<2.0.0)
Requires-Dist: paramiko (>=3.4.0,<4.0.0)
Requires-Dist: pymysql (>=1.1.0,<2.0.0)
Requires-Dist: trading-ig (>=0.0.22,<0.0.23)
